[
  {
    "hadith_id": 270991,
    "book_id": 277,
    "book_name_ar": "كتاب رقم 277",
    "book_name_en": "Book 277 (Unknown Collection)",
    "author_name_ar": "مؤلف غير معروف",
    "author_name_en": "Unknown Author",
    "hadith_number": "2194",
    "english_translation": "Narrated by Anas ibn Malik: The Prophet ﷺ established brotherhood (alliance) between the Muhajirin and the Ansar in my house which is in Al-Madinah.",
    "chains": [
      {
        "type": "marfu'",
        "narrators": [
          {
            "name": "Abu Bakr ibn Abi Shaybah",
            "full_name": "Abdullah ibn Muhammad ibn Uthman ibn Abi Shaybah al-Kufi",
            "grade": "Thabt Hafiz",
            "generation": "Eighth Generation",
            "transmissionTerm": "حَدَّثَنَا",
            "transmissionTermMeaning": "He narrated to us (direct hearing)",
            "reliabilityIssues": [],
            "narrator_id": 5049,
            "alternative_names": "Abu Bakr al-Kufi, Ibn Abi Shaybah",
            "original_id": 4235,
            "kunya": "Abu Bakr",
            "nisba": "al-Kufi",
            "nisba_ar": "الكوفي",
            "death_year": "235",
            "birth_year": "159",
            "reliability_grade": "Thabt Hafiz",
            "tabaqat": "8",
            "location": "Kufa"
          },
          {
            "name": "Abdat ibn Sulayman",
            "full_name": "Abdat ibn Sulayman ibn Tarkhān al-Tāʾī",
            "grade": "Saduq",
            "generation": "Seventh Generation",
            "transmissionTerm": "نَا",
            "transmissionTermMeaning": "He narrated to us (direct hearing)",
            "reliabilityIssues": [],
            "narrator_id": 5288,
            "alternative_names": "Abdat al-Tai",
            "original_id": 4480,
            "kunya": "Abu Muhammad",
            "nisba": "al-Tai",
            "nisba_ar": "الطائي",
            "death_year": "220",
            "birth_year": "141",
            "reliability_grade": "Saduq",
            "tabaqat": "7",
            "location": "Khorasan"
          },
          {
            "name": "Asim",
            "full_name": "Asim ibn Abi al-Najud Bahdalah ibn Abi Isa al-Asadi",
            "grade": "Saduq",
            "generation": "Fifth Generation",
            "transmissionTerm": "عَنْ",
            "transmissionTermMeaning": "From (could be direct or indirect)",
            "reliabilityIssues": [
              "not of highest reliability"
            ],
            "narrator_id": 4064,
            "alternative_names": "Asim al-Qari, Bahdalah",
            "original_id": 3224,
            "kunya": "Abu Isa",
            "nisba": "al-Asadi",
            "nisba_ar": "الأسدي",
            "death_year": "127",
            "birth_year": "",
            "reliability_grade": "Saduq",
            "tabaqat": "5",
            "location": "Kufa"
          },
          {
            "name": "Anas ibn Malik",
            "full_name": "Anas ibn Malik ibn al-Nadr al-Ansari",
            "grade": "Thiqah Thabt",
            "generation": "Companion",
            "transmissionTerm": "عَنْ",
            "transmissionTermMeaning": "From",
            "reliabilityIssues": [],
            "narrator_id": 720,
            "alternative_names": "Anas al-Ansari",
            "original_id": 720,
            "kunya": "Abu Hamza",
            "nisba": "al-Ansari",
            "nisba_ar": "الأنصاري",
            "death_year": "93",
            "birth_year": "10",
            "reliability_grade": "Thiqah Thabt",
            "tabaqat": "Companion",
            "location": "Al-Madinah"
          },
          {
            "name": "Prophet Muhammad ﷺ",
            "full_name": "Muhammad ibn Abdullah ibn Abd al-Muttalib ibn Hashim",
            "grade": "Awthaq al-Nas",
            "generation": "Prophet",
            "transmissionTerm": "",
            "transmissionTermMeaning": "",
            "reliabilityIssues": [],
            "narrator_id": 0,
            "alternative_names": "Ahmad, al-Mustafa",
            "original_id": 0,
            "kunya": "Abu al-Qasim",
            "nisba": "al-Hashimi",
            "nisba_ar": "الهاشمي",
            "death_year": "11",
            "birth_year": "53 BH",
            "reliability_grade": "Awthaq al-Nas",
            "tabaqat": "Prophet",
            "location": "Makkah/Al-Madinah"
          }
        ],
        "chainIssues": [
          "Asim uses 'an (عَنْ) with Abdat, and while Asim is Saduq he is not of highest reliability",
          "Gap between Asim and Anas in the chain - possible indirect transmission"
        ]
      }
    ],
    "potential_issues": [
      {
        "issue": "Asim (Saduq) narrates from Abdat using 'an (عَنْ)",
        "impact": "Introduces some ambiguity in the connection, though Saduq narrators with 'an are generally acceptable when not known mudallis"
      },
      {
        "issue": "Abdat ibn Sulayman is rated Saduq, not Thiqah",
        "impact": "Reduces reliability of the chain slightly, though not severely problematic"
      },
      {
        "issue": "Incomplete narrator information in source data",
        "impact": "Some narrator details had to be reconstructed from known historical records"
      }
    ],
    "Classical Grade": [
      "Hasan"
    ],
    "IISGrade": "Acceptable",
    "Topics": [
      "Incident of establishing brotherhood between Muhajirin and Ansar",
      "The Prophet's ﷺ action of making alliances at Anas's house in Al-Madinah"
    ]
  },
  {
    "hadith_id": 270992,
    "book_id": 277,
    "book_name_ar": "كتاب رقم 277",
    "book_name_en": "Book 277 (Unknown Collection)",
    "author_name_ar": "مؤلف غير معروف",
    "author_name_en": "Unknown Author",
    "hadith_number": "2195",
    "english_translation": "Chapter heading: Mention of the Prophet's ﷺ statement regarding all houses of the Ansar being good.",
    "chains": [],
    "potential_issues": [
      {
        "issue": "This is a chapter heading, not a hadith with a chain",
        "impact": "No chain of transmission to evaluate"
      }
    ],
    "Classical Grade": [
      "Daif"
    ],
    "IISGrade": "Disconnections But All Narrators Are Ok",
    "Topics": [
      "The merit and goodness of all Ansar houses mentioned by the Prophet ﷺ"
    ]
  },
  {
    "hadith_id": 270993,
    "book_id": 277,
    "book_name_ar": "كتاب رقم 277",
    "book_name_en": "Book 277 (Unknown Collection)",
    "author_name_ar": "مؤلف غير معروف",
    "author_name_en": "Unknown Author",
    "hadith_number": "2196",
    "english_translation": "Narrated by Abu Usayd al-Sa'idi (or his father): The Prophet ﷺ was asked: Which houses of the Ansar are best? He said: The houses of Banu al-Najjar, then Banu al-Ashhal, then Banu al-Harith ibn al-Khazraj, then Banu Sa'idah. He then said: In all houses of the Ansar there is good.",
    "chains": [
      {
        "type": "marfu'",
        "narrators": [
          {
            "name": "Ya'qub ibn Hamid",
            "full_name": "Ya'qub ibn Hamid ibn Umarah al-Basri",
            "grade": "Saduq",
            "generation": "Eighth Generation",
            "transmissionTerm": "حَدَّثَنَا",
            "transmissionTermMeaning": "He narrated to us (direct hearing)",
            "reliabilityIssues": [],
            "narrator_id": 8521,
            "alternative_names": "Ya'qub ibn Hamid al-Basri",
            "original_id": 7791,
            "kunya": "Abu Ibrahim",
            "nisba": "al-Basri",
            "nisba_ar": "البصري",
            "death_year": "228",
            "birth_year": "150",
            "reliability_grade": "Saduq",
            "tabaqat": "8",
            "location": "Basra"
          },
          {
            "name": "Ibn Abi Uways",
            "full_name": "Abdullah ibn Muhammad ibn Abi Uways al-Medini al-Asbahi",
            "grade": "Saduq",
            "generation": "Seventh Generation",
            "transmissionTerm": "نَا",
            "transmissionTermMeaning": "He narrated to us (direct hearing)",
            "reliabilityIssues": [],
            "narrator_id": 1040,
            "alternative_names": "Abd Allah ibn Muhammad al-Medini",
            "original_id": 116,
            "kunya": "Abu Muhammad",
            "nisba": "al-Medini",
            "nisba_ar": "المديني",
            "death_year": "213",
            "birth_year": "135",
            "reliability_grade": "Saduq",
            "tabaqat": "7",
            "location": "Al-Madinah"
          },
          {
            "name": "His father (Muhammad ibn Abi Uways)",
            "full_name": "Muhammad ibn Abi Uways al-Asbahi",
            "grade": "Saduq",
            "generation": "Sixth Generation",
            "transmissionTerm": "نَا",
            "transmissionTermMeaning": "He narrated to us (direct hearing)",
            "reliabilityIssues": [],
            "narrator_id": 4916,
            "alternative_names": "Muhammad ibn Abi Uways",
            "original_id": 4096,
            "kunya": "Abu Bakr",
            "nisba": "al-Asbahi",
            "nisba_ar": "الأصبحي",
            "death_year": "213",
            "birth_year": "125",
            "reliability_grade": "Saduq",
            "tabaqat": "6",
            "location": "Al-Madinah"
          },
          {
            "name": "Musa ibn Amr ibn Abdullah",
            "full_name": "Musa ibn Amr ibn Abdullah ibn Abi Haram al-Ansari min Bani Dinar",
            "grade": "Majhul",
            "generation": "Fourth Generation",
            "transmissionTerm": "عَنْ",
            "transmissionTermMeaning": "From (could be direct or indirect)",
            "reliabilityIssues": [
              "majhul - obscure narrator with no clear reliability assessment"
            ],
            "narrator_id": 32405,
            "alternative_names": "Musa ibn Amr al-Ansari",
            "original_id": 51244,
            "kunya": "",
            "nisba": "al-Ansari",
            "nisba_ar": "الأنصاري",
            "death_year": "",
            "birth_year": "",
            "reliability_grade": "Majhul",
            "tabaqat": "4",
            "location": "Al-Madinah"
          },
          {
            "name": "Hamzah ibn Abi Usayd al-Sa'idi",
            "full_name": "Hamzah ibn Abi Usayd al-Sa'idi al-Ansari",
            "grade": "Saduq",
            "generation": "Third Generation",
            "transmissionTerm": "عَنْ",
            "transmissionTermMeaning": "From (could be direct or indirect)",
            "reliabilityIssues": [],
            "narrator_id": 2507,
            "alternative_names": "Hamzah al-Sa'idi",
            "original_id": 1621,
            "kunya": "Abu Sa'id",
            "nisba": "al-Sa'idi",
            "nisba_ar": "الساعدي",
            "death_year": "104",
            "birth_year": "",
            "reliability_grade": "Saduq",
            "tabaqat": "3",
            "location": "Al-Madinah"
          },
          {
            "name": "His father (Abu Usayd al-Sa'idi)",
            "full_name": "Malik ibn Sinan al-Sa'idi al-Ansari",
            "grade": "Thiqah Thabt",
            "generation": "Companion",
            "transmissionTerm": "عَنْ",
            "transmissionTermMeaning": "From",
            "reliabilityIssues": [],
            "narrator_id": 6674,
            "alternative_names": "Abu Usayd al-Sa'idi",
            "original_id": 5905,
            "kunya": "Abu Usayd",
            "nisba": "al-Sa'idi",
            "nisba_ar": "الساعدي",
            "death_year": "74",
            "birth_year": "",
            "reliability_grade": "Thiqah Thabt",
            "tabaqat": "Companion",
            "location": "Al-Madinah"
          },
          {
            "name": "Prophet Muhammad ﷺ",
            "full_name": "Muhammad ibn Abdullah ibn Abd al-Muttalib ibn Hashim",
            "grade": "Awthaq al-Nas",
            "generation": "Prophet",
            "transmissionTerm": "",
            "transmissionTermMeaning": "",
            "reliabilityIssues": [],
            "narrator_id": 0,
            "alternative_names": "Ahmad, al-Mustafa",
            "original_id": 0,
            "kunya": "Abu al-Qasim",
            "nisba": "al-Hashimi",
            "nisba_ar": "الهاشمي",
            "death_year": "11",
            "birth_year": "53 BH",
            "reliability_grade": "Awthaq al-Nas",
            "tabaqat": "Prophet",
            "location": "Makkah/Al-Madinah"
          }
        ],
        "chainIssues": [
          "Musa ibn Amr ibn Abdullah is Majhul (obscure), which weakens the chain significantly",
          "Multiple Saduq narrators without direct transmission in parts of the chain"
        ]
      }
    ],
    "potential_issues": [
      {
        "issue": "Musa ibn Amr ibn Abdullah is rated Majhul (obscure narrator)",
        "impact": "Significantly weakens the chain as this narrator's reliability is unknown and only mentioned in this transmission"
      },
      {
        "issue": "Chain contains several Saduq-graded narrators (Ya'qub, Ibn Abi Uways, Muhammad ibn Abi Uways, Hamzah)",
        "impact": "Reduces overall reliability from Perfect or Sound level to Acceptable or Weak"
      },
      {
        "issue": "Use of عَنْ (an) from Saduq narrators with Majhul Musa ibn Amr",
        "impact": "Introduces ambiguity in transmission connection and weakens the chain further"
      }
    ],
    "Classical Grade": [
      "Daif"
    ],
    "IISGrade": "Weak But Might Be Acceptable",
    "Topics": [
      "The Prophet's ﷺ comparison of Ansar houses in terms of merit",
      "Ranking of Banu al-Najjar, Banu al-Ashhal, Banu al-Harith, and Banu Sa'idah",
      "Statement that all houses of Ansar are good"
    ]
  },
  {
    "hadith_id": 270994,
    "book_id": 277,
    "book_name_ar": "كتاب رقم 277",
    "book_name_en": "Book 277 (Unknown Collection)",
    "author_name_ar": "مؤلف غير معروف",
    "author_name_en": "Unknown Author",
    "hadith_number": "2197",
    "english_translation": "Narrated by Abu Usayd al-Sa'idi: The Prophet ﷺ said: The best houses of the Ansar are: Banu al-Najjar, then Banu Abd al-Ashhal, then Banu Sa'idah, then Banu al-Harith ibn al-Khazraj.",
    "chains": [
      {
        "type": "marfu'",
        "narrators": [
          {
            "name": "Abu Bakr ibn Abi Shaybah",
            "full_name": "Abdullah ibn Muhammad ibn Uthman ibn Abi Shaybah al-Kufi",
            "grade": "Thabt Hafiz",
            "generation": "Eighth Generation",
            "transmissionTerm": "حَدَّثَنَا",
            "transmissionTermMeaning": "He narrated to us (direct hearing)",
            "reliabilityIssues": [],
            "narrator_id": 5049,
            "alternative_names": "Abu Bakr al-Kufi",
            "original_id": 4235,
            "kunya": "Abu Bakr",
            "nisba": "al-Kufi",
            "nisba_ar": "الكوفي",
            "death_year": "235",
            "birth_year": "159",
            "reliability_grade": "Thabt Hafiz",
            "tabaqat": "8",
            "location": "Kufa"
          },
          {
            "name": "Abd al-Rahman ibn Mahdi",
            "full_name": "Abd al-Rahman ibn Muhammad ibn Saʿid ibn Abjar al-ʿAnbari",
            "grade": "Thabt Hafiz",
            "generation": "Seventh Generation",
            "transmissionTerm": "ثنا",
            "transmissionTermMeaning": "He narrated to us (direct hearing)",
            "reliabilityIssues": [],
            "narrator_id": 4493,
            "alternative_names": "Abd al-Rahman al-Basri, Ibn Mahdi",
            "original_id": 3660,
            "kunya": "Abu al-Qasim",
            "nisba": "al-Basri",
            "nisba_ar": "البصري",
            "death_year": "198",
            "birth_year": "135",
            "reliability_grade": "Thabt Hafiz",
            "tabaqat": "7",
            "location": "Basra"
          },
          {
            "name": "Sufyan (al-Thawri)",
            "full_name": "Sufyan ibn Said ibn Masruq al-Thawri",
            "grade": "Thabt Hafiz",
            "generation": "Sixth Generation",
            "transmissionTerm": "ثنا",
            "transmissionTermMeaning": "He narrated to us (direct hearing)",
            "reliabilityIssues": [],
            "narrator_id": 3436,
            "alternative_names": "Sufyan al-Thawri, Abu Abd Allah",
            "original_id": 2578,
            "kunya": "Abu Abd Allah",
            "nisba": "al-Thawri",
            "nisba_ar": "الثوري",
            "death_year": "161",
            "birth_year": "97",
            "reliability_grade": "Thabt Hafiz",
            "tabaqat": "6",
            "location": "Kufa"
          },
          {
            "name": "Abu al-Zinad",
            "full_name": "Abdullah ibn Dinar al-Aswadi al-Medini",
            "grade": "Thabt Hafiz",
            "generation": "Fourth Generation",
            "transmissionTerm": "عَنْ",
            "transmissionTermMeaning": "From (could be direct or indirect)",
            "reliabilityIssues": [],
            "narrator_id": 4798,
            "alternative_names": "Abdullah ibn Dinar, Abu al-Zinad",
            "original_id": 3972,
            "kunya": "Abu al-Zinad",
            "nisba": "al-Medini",
            "nisba_ar": "المديني",
            "death_year": "174",
            "birth_year": "81",
            "reliability_grade": "Thabt Hafiz",
            "tabaqat": "4",
            "location": "Al-Madinah"
          },
          {
            "name": "Abu Salamah",
            "full_name": "Abd al-Rahman ibn Abd al-Qari al-Umayyad al-Medini",
            "grade": "Thabt Hafiz",
            "generation": "Third Generation",
            "transmissionTerm": "عَنْ",
            "transmissionTermMeaning": "From (could be direct or indirect)",
            "reliabilityIssues": [],
            "narrator_id": 4903,
            "alternative_names": "Abd al-Rahman ibn Abd al-Qari, Abu Salamah",
            "original_id": 4083,
            "kunya": "Abu Salamah",
            "nisba": "al-Umayyad",
            "nisba_ar": "الأموي",
            "death_year": "94",
            "birth_year": "30",
            "reliability_grade": "Thabt Hafiz",
            "tabaqat": "3",
            "location": "Al-Madinah"
          },
          {
            "name": "Abu Usayd al-Sa'idi",
            "full_name": "Malik ibn Sinan al-Sa'idi al-Ansari",
            "grade": "Thiqah Thabt",
            "generation": "Companion",
            "transmissionTerm": "عَنْ",
            "transmissionTermMeaning": "From",
            "reliabilityIssues": [],
            "narrator_id": 6674,
            "alternative_names": "Abu Usayd al-Sa'idi",
            "original_id": 5905,
            "kunya": "Abu Usayd",
            "nisba": "al-Sa'idi",
            "nisba_ar": "الساعدي",
            "death_year": "74",
            "birth_year": "",
            "reliability_grade": "Thiqah Thabt",
            "tabaqat": "Companion",
            "location": "Al-Madinah"
          },
          {
            "name": "Prophet Muhammad ﷺ",
            "full_name": "Muhammad ibn Abdullah ibn Abd al-Muttalib ibn Hashim",
            "grade": "Awthaq al-Nas",
            "generation": "Prophet",
            "transmissionTerm": "",
            "transmissionTermMeaning": "",
            "reliabilityIssues": [],
            "narrator_id": 0,
            "alternative_names": "Ahmad, al-Mustafa",
            "original_id": 0,
            "kunya": "Abu al-Qasim",
            "nisba": "al-Hashimi",
            "nisba_ar": "الهاشمي",
            "death_year": "11",
            "birth_year": "53 BH",
            "reliability_grade": "Awthaq al-Nas",
            "tabaqat": "Prophet",
            "location": "Makkah/Al-Madinah"
          }
        ],
        "chainIssues": []
      }
    ],
    "potential_issues": [],
    "Classical Grade": [
      "Sahih"
    ],
    "IISGrade": "Sound",
    "Topics": [
      "The Prophet's ﷺ ranking of Ansar houses",
      "Merit of Banu al-Najjar being the best among Ansar",
      "Comparison of Ansar houses in terms of virtue"
    ]
  },
  {
    "hadith_id": 270995,
    "book_id": 277,
    "book_name_ar": "كتاب رقم 277",
    "book_name_en": "Book 277 (Unknown Collection)",
    "author_name_ar": "مؤلف غير معروف",
    "author_name_en": "Unknown Author",
    "hadith_number": "2198",
    "english_translation": "Narrated by Anas ibn Malik and Abu Usayd al-Sa'idi: The Prophet ﷺ said: The best houses of the Ansar are: Banu al-Najjar, then Banu Abd al-Ashhal, then Banu al-Harith ibn al-Khazraj, then Banu Sa'idah, and in all houses of the Ansar there is good. Then Saad ibn Mu'adh said: I do not see the Messenger of Allah ﷺ except that he has placed us (Banu Sa'idah) at the end.",
    "chains": [
      {
        "type": "marfu'",
        "narrators": [
          {
            "name": "Abu Musa al-Ash'ari",
            "full_name": "Abdullah ibn Qays ibn Sulaim al-Ash'ari",
            "grade": "Thabt Hafiz",
            "generation": "Eighth Generation",
            "transmissionTerm": "حَدَّثَنَا",
            "transmissionTermMeaning": "He narrated to us (direct hearing)",
            "reliabilityIssues": [],
            "narrator_id": 6861,
            "alternative_names": "Abu Musa al-Ash'ari",
            "original_id": 6096,
            "kunya": "Abu Musa",
            "nisba": "al-Ash'ari",
            "nisba_ar": "الأشعري",
            "death_year": "245",
            "birth_year": "162",
            "reliability_grade": "Thabt Hafiz",
            "tabaqat": "8",
            "location": "Basra"
          },
          {
            "name": "Muhammad ibn Jafar",
            "full_name": "Muhammad ibn Jafar ibn Muhammad ibn al-Hajjaj al-Misri",
            "grade": "Saduq",
            "generation": "Seventh Generation",
            "transmissionTerm": "ثنا",
            "transmissionTermMeaning": "He narrated to us (direct hearing)",
            "reliabilityIssues": [],
            "narrator_id": 6904,
            "alternative_names": "Muhammad ibn Jafar al-Misri",
            "original_id": 6140,
            "kunya": "Abu Muhammad",
            "nisba": "al-Misri",
            "nisba_ar": "المصري",
            "death_year": "226",
            "birth_year": "147",
            "reliability_grade": "Saduq",
            "tabaqat": "7",
            "location": "Egypt"
          },
          {
            "name": "Shu'bah",
            "full_name": "Shu'bah ibn al-Hajjaj ibn al-Ward al-Ataki al-Azdi",
            "grade": "Thabt Hafiz",
            "generation": "Sixth Generation",
            "transmissionTerm": "نَا",
            "transmissionTermMeaning": "He narrated to us (direct hearing)",
            "reliabilityIssues": [],
            "narrator_id": 3795,
            "alternative_names": "Abu Bistam al-Ataki",
            "original_id": 2945,
            "kunya": "Abu Bistam",
            "nisba": "al-Ataki",
            "nisba_ar": "العتكي",
            "death_year": "160",
            "birth_year": "83",
            "reliability_grade": "Thabt Hafiz",
            "tabaqat": "6",
            "location": "Basra"
          },
          {
            "name": "Qatadah",
            "full_name": "Qatadah ibn Damamah al-Sadusi al-Basri",
            "grade": "Thabt Hafiz",
            "generation": "Fourth Generation",
            "transmissionTerm": "عَنْ",
            "transmissionTermMeaning": "From (could be direct or indirect)",
            "reliabilityIssues": [
              "mudallis - classified as category 3 mudallis by Ibn Hajar"
            ],
            "narrator_id": 6458,
            "alternative_names": "Qatadah al-Basri",
            "original_id": 5683,
            "kunya": "Abu al-Khattab",
            "nisba": "al-Basri",
            "nisba_ar": "البصري",
            "death_year": "118",
            "birth_year": "61",
            "reliability_grade": "Thabt Hafiz",
            "tabaqat": "4",
            "location": "Basra"
          },
          {
            "name": "Anas ibn Malik",
            "full_name": "Anas ibn Malik ibn al-Nadr al-Ansari",
            "grade": "Thiqah Thabt",
            "generation": "Companion",
            "transmissionTerm": "عَنْ",
            "transmissionTermMeaning": "From",
            "reliabilityIssues": [],
            "narrator_id": 720,
            "alternative_names": "Anas al-Ansari",
            "original_id": 720,
            "kunya": "Abu Hamza",
            "nisba": "al-Ansari",
            "nisba_ar": "الأنصاري",
            "death_year": "93",
            "birth_year": "10",
            "reliability_grade": "Thiqah Thabt",
            "tabaqat": "Companion",
            "location": "Al-Madinah"
          },
          {
            "name": "Abu Usayd al-Sa'idi",
            "full_name": "Malik ibn Sinan al-Sa'idi al-Ansari",
            "grade": "Thiqah Thabt",
            "generation": "Companion",
            "transmissionTerm": "عَنْ",
            "transmissionTermMeaning": "From",
            "reliabilityIssues": [],
            "narrator_id": 6674,
            "alternative_names": "Abu Usayd al-Sa'idi",
            "original_id": 5905,
            "kunya": "Abu Usayd",
            "nisba": "al-Sa'idi",
            "nisba_ar": "الساعدي",
            "death_year": "74",
            "birth_year": "",
            "reliability_grade": "Thiqah Thabt",
            "tabaqat": "Companion",
            "location": "Al-Madinah"
          },
          {
            "name": "Prophet Muhammad ﷺ",
            "full_name": "Muhammad ibn Abdullah ibn Abd al-Muttalib ibn Hashim",
            "grade": "Awthaq al-Nas",
            "generation": "Prophet",
            "transmissionTerm": "",
            "transmissionTermMeaning": "",
            "reliabilityIssues": [],
            "narrator_id": 0,
            "alternative_names": "Ahmad, al-Mustafa",
            "original_id": 0,
            "kunya": "Abu al-Qasim",
            "nisba": "al-Hashimi",
            "nisba_ar": "الهاشمي",
            "death_year": "11",
            "birth_year": "53 BH",
            "reliability_grade": "Awthaq al-Nas",
            "tabaqat": "Prophet",
            "location": "Makkah/Al-Madinah"
          }
        ],
        "chainIssues": [
          "Qatadah is a known mudallis (category 3) who uses 'an (عَنْ) with Anas - however, Qatadah is still Thabt (reliable) and this is acceptable per classical hadith principles as his tadlis is not severe",
          "Muhammad ibn Jafar is Saduq, not Thabt"
        ]
      }
    ],
    "potential_issues": [
      {
        "issue": "Qatadah is classified as a category 3 mudallis by Ibn Hajar and uses 'an (عَنْ) with Anas",
        "impact": "While Qatadah's tadlis is a concern, he is still Thabt (reliable) and many scholars accept his narrations, especially with Anas who he is known to have heard from. This does not significantly affect the overall reliability grade"
      },
      {
        "issue": "Muhammad ibn Jafar is Saduq, not Thiqah",
        "impact": "Slightly reduces the chain reliability but not significantly problematic given the strength of other narrators"
      }
    ],
    "Classical Grade": [
      "Hasan"
    ],
    "IISGrade": "Acceptable",
    "Topics": [
      "The Prophet's ﷺ praise of Ansar houses",
      "Ranking and comparison of Ansar tribes by the Prophet ﷺ",
      "Incident of Saad ibn Mu'adh feeling concerned about his tribe's position"
    ]
  },
  {
    "hadith_id": 270996,
    "book_id": 277,
    "book_name_ar": "كتاب رقم 277",
    "book_name_en": "Book 277 (Unknown Collection)",
    "author_name_ar": "مؤلف غير معروف",
    "author_name_en": "Unknown Author",
    "hadith_number": "2199",
    "english_translation": "Narrated by Anas ibn Malik: The Prophet ﷺ said: Shall I not inform you of the best houses of the Ansar? Banu al-Najjar, then those who are near them (from) Banu Abd al-Ashhal, then those who are near them (from) Banu al-Harith ibn al-Khazraj, then those who are near them (from) Banu Sa'idah. And in all houses of the Ansar there is good.",
    "chains": [
      {
        "type": "marfu'",
        "narrators": [
          {
            "name": "Abu al-Rabi' al-Zahrani",
            "full_name": "Khalaf ibn Tamim ibn Malik al-Tammimi al-Kufi",
            "grade": "Thabt Hafiz",
            "generation": "Eighth Generation",
            "transmissionTerm": "حَدَّثَنَا",
            "transmissionTermMeaning": "He narrated to us (direct hearing)",
            "reliabilityIssues": [],
            "narrator_id": 3583,
            "alternative_names": "Abu al-Rabi al-Zahrani, Khalaf al-Kufi",
            "original_id": 2731,
            "kunya": "Abu Abd al-Rahman",
            "nisba": "al-Zahrani",
            "nisba_ar": "الزهراني",
            "death_year": "222",
            "birth_year": "145",
            "reliability_grade": "Thabt Hafiz",
            "tabaqat": "8",
            "location": "Kufa"
          },
          {
            "name": "Hammad ibn Zayd",
            "full_name": "Hammad ibn Zayd ibn Dirham al-Azdi al-Basri",
            "grade": "Thabt Hafiz",
            "generation": "Sixth Generation",
            "transmissionTerm": "ثنا",
            "transmissionTermMeaning": "He narrated to us (direct hearing)",
            "reliabilityIssues": [],
            "narrator_id": 2491,
            "alternative_names": "Hammad al-Basri",
            "original_id": 1604,
            "kunya": "Abu Isa",
            "nisba": "al-Azdi",
            "nisba_ar": "الأزدي",
            "death_year": "179",
            "birth_year": "102",
            "reliability_grade": "Thabt Hafiz",
            "tabaqat": "6",
            "location": "Basra"
          },
          {
            "name": "Yahya ibn Saeed al-Qattan",
            "full_name": "Yahya ibn Saeed ibn Farruakh al-Tamimi al-Basri",
            "grade": "Thabt Hafiz",
            "generation": "Fifth Generation",
            "transmissionTerm": "عَنْ",
            "transmissionTermMeaning": "From (could be direct or indirect)",
            "reliabilityIssues": [],
            "narrator_id": 8272,
            "alternative_names": "Yahya al-Qattan",
            "original_id": 7533,
            "kunya": "Abu Zakariya",
            "nisba": "al-Basri",
            "nisba_ar": "البصري",
            "death_year": "198",
            "birth_year": "120",
            "reliability_grade": "Thabt Hafiz",
            "tabaqat": "5",
            "location": "Basra"
          },
          {
            "name": "Anas ibn Malik",
            "full_name": "Anas ibn Malik ibn al-Nadr al-Ansari",
            "grade": "Thiqah Thabt",
            "generation": "Companion",
            "transmissionTerm": "عَنْ",
            "transmissionTermMeaning": "From",
            "reliabilityIssues": [],
            "narrator_id": 720,
            "alternative_names": "Anas al-Ansari",
            "original_id": 720,
            "kunya": "Abu Hamza",
            "nisba": "al-Ansari",
            "nisba_ar": "الأنصاري",
            "death_year": "93",
            "birth_year": "10",
            "reliability_grade": "Thiqah Thabt",
            "tabaqat": "Companion",
            "location": "Al-Madinah"
          },
          {
            "name": "Prophet Muhammad ﷺ",
            "full_name": "Muhammad ibn Abdullah ibn Abd al-Muttalib ibn Hashim",
            "grade": "Awthaq al-Nas",
            "generation": "Prophet",
            "transmissionTerm": "",
            "transmissionTermMeaning": "",
            "reliabilityIssues": [],
            "narrator_id": 0,
            "alternative_names": "Ahmad, al-Mustafa",
            "original_id": 0,
            "kunya": "Abu al-Qasim",
            "nisba": "al-Hashimi",
            "nisba_ar": "الهاشمي",
            "death_year": "11",
            "birth_year": "53 BH",
            "reliability_grade": "Awthaq al-Nas",
            "tabaqat": "Prophet",
            "location": "Makkah/Al-Madinah"
          }
        ],
        "chainIssues": []
      }
    ],
    "potential_issues": [],
    "Classical Grade": [
      "Sahih"
    ],
    "IISGrade": "Sound",
    "Topics": [
      "The Prophet's ﷺ declaration about the best Ansar houses",
      "Ranking of Ansar houses with Banu al-Najjar at the top",
      "Emphasis on the merit of all Ansar houses"
    ]
  },
  {
    "hadith_id": 270997,
    "book_id": 277,
    "book_name_ar": "كتاب رقم 277",
    "book_name_en": "Book 277 (Unknown Collection)",
    "author_name_ar": "مؤلف غير معروف",
    "author_name_en": "Unknown Author",
    "hadith_number": "2200",
    "english_translation": "Narrated by Anas ibn Malik: The Prophet ﷺ said: Shall I not inform you of the best houses of the Ansar? The houses of Banu al-Najjar, and the houses of Banu Harithah, and the houses of Banu Abd al-Ashhal, then the houses of Banu al-Harith ibn al-Khazraj, then the houses of Banu Sa'idah, and in all houses of the Ansar there is good.",
    "chains": [
      {
        "type": "marfu'",
        "narrators": [
          {
            "name": "Wahban",
            "full_name": "Wahban ibn Baqi'ah al-Hanaʾi",
            "grade": "Saduq",
            "generation": "Eighth Generation",
            "transmissionTerm": "حَدَّثَنَا",
            "transmissionTermMeaning": "He narrated to us (direct hearing)",
            "reliabilityIssues": [],
            "narrator_id": 8166,
            "alternative_names": "Wahban al-Hanaʾi, Abu Hammam",
            "original_id": 7423,
            "kunya": "Abu Hammam",
            "nisba": "al-Hanaʾi",
            "nisba_ar": "الهنائي",
            "death_year": "235",
            "birth_year": "160",
            "reliability_grade": "Saduq",
            "tabaqat": "8",
            "location": "Kufa"
          },
          {
            "name": "Khalid",
            "full_name": "Khalid ibn Usamah al-Hamdani",
            "grade": "Saduq Lahu Awham",
            "generation": "Seventh Generation",
            "transmissionTerm": "ثنا",
            "transmissionTermMeaning": "He narrated to us (direct hearing)",
            "reliabilityIssues": [
              "has confusion in his narrations"
            ],
            "narrator_id": 2663,
            "alternative_names": "Khalid al-Hamdani",
            "original_id": 1779,
            "kunya": "Abu Usamah",
            "nisba": "al-Hamdani",
            "nisba_ar": "الهمداني",
            "death_year": "208",
            "birth_year": "129",
            "reliability_grade": "Saduq Lahu Awham",
            "tabaqat": "7",
            "location": "Kufa"
          },
          {
            "name": "Humaid",
            "full_name": "Humaid ibn Abi Humaid al-Tawil al-Basri",
            "grade": "Saduq",
            "generation": "Fifth Generation",
            "transmissionTerm": "عَنْ",
            "transmissionTermMeaning": "From (could be direct or indirect)",
            "reliabilityIssues": [],
            "narrator_id": 2531,
            "alternative_names": "Humaid al-Basri, Humaid al-Tawil",
            "original_id": 1645,
            "kunya": "Abu Muhammad",
            "nisba": "al-Basri",
            "nisba_ar": "البصري",
            "death_year": "148",
            "birth_year": "69",
            "reliability_grade": "Saduq",
            "tabaqat": "5",
            "location": "Basra"
          },
          {
            "name": "Anas ibn Malik",
            "full_name": "Anas ibn Malik ibn al-Nadr al-Ansari",
            "grade": "Thiqah Thabt",
            "generation": "Companion",
            "transmissionTerm": "عَنْ",
            "transmissionTermMeaning": "From",
            "reliabilityIssues": [],
            "narrator_id": 720,
            "alternative_names": "Anas al-Ansari",
            "original_id": 720,
            "kunya": "Abu Hamza",
            "nisba": "al-Ansari",
            "nisba_ar": "الأنصاري",
            "death_year": "93",
            "birth_year": "10",
            "reliability_grade": "Thiqah Thabt",
            "tabaqat": "Companion",
            "location": "Al-Madinah"
          },
          {
            "name": "Prophet Muhammad ﷺ",
            "full_name": "Muhammad ibn Abdullah ibn Abd al-Muttalib ibn Hashim",
            "grade": "Awthaq al-Nas",
            "generation": "Prophet",
            "transmissionTerm": "",
            "transmissionTermMeaning": "",
            "reliabilityIssues": [],
            "narrator_id": 0,
            "alternative_names": "Ahmad, al-Mustafa",
            "original_id": 0,
            "kunya": "Abu al-Qasim",
            "nisba": "al-Hashimi",
            "nisba_ar": "الهاشمي",
            "death_year": "11",
            "birth_year": "53 BH",
            "reliability_grade": "Awthaq al-Nas",
            "tabaqat": "Prophet",
            "location": "Makkah/Al-Madinah"
          }
        ],
        "chainIssues": [
          "Khalid ibn Usamah is rated Saduq Lahu Awham (has confusion)",
          "Humaid narrates from Anas with 'an (عَنْ)",
          "Multiple Saduq narrators in the chain"
        ]
      },
      {
        "type": "marfu'",
        "narrators": [
          {
            "name": "Abu Bakr ibn Abi Shaybah",
            "full_name": "Abdullah ibn Muhammad ibn Uthman ibn Abi Shaybah al-Kufi",
            "grade": "Thabt Hafiz",
            "generation": "Eighth Generation",
            "transmissionTerm": "حَدَّثَنَا",
            "transmissionTermMeaning": "He narrated to us (direct hearing)",
            "reliabilityIssues": [],
            "narrator_id": 5049,
            "alternative_names": "Abu Bakr al-Kufi",
            "original_id": 4235,
            "kunya": "Abu Bakr",
            "nisba": "al-Kufi",
            "nisba_ar": "الكوفي",
            "death_year": "235",
            "birth_year": "159",
            "reliability_grade": "Thabt Hafiz",
            "tabaqat": "8",
            "location": "Kufa"
          },
          {
            "name": "Yazid ibn Harun",
            "full_name": "Yazid ibn Harun ibn Yazid al-Sulami al-Wasiti",
            "grade": "Thabt Hafiz",
            "generation": "Seventh Generation",
            "transmissionTerm": "نَا",
            "transmissionTermMeaning": "He narrated to us (direct hearing)",
            "reliabilityIssues": [],
            "narrator_id": 8488,
            "alternative_names": "Yazid al-Wasiti",
            "original_id": 7771,
            "kunya": "Abu Khalid",
            "nisba": "al-Wasiti",
            "nisba_ar": "الواسطي",
            "death_year": "206",
            "birth_year": "129",
            "reliability_grade": "Thabt Hafiz",
            "tabaqat": "7",
            "location": "Wasit"
          },
          {
            "name": "Humaid",
            "full_name": "Humaid ibn Abi Humaid al-Tawil al-Basri",
            "grade": "Saduq",
            "generation": "Fifth Generation",
            "transmissionTerm": "نَا",
            "transmissionTermMeaning": "He narrated to us (direct hearing)",
            "reliabilityIssues": [],
            "narrator_id": 2531,
            "alternative_names": "Humaid al-Basri",
            "original_id": 1645,
            "kunya": "Abu Muhammad",
            "nisba": "al-Basri",
            "nisba_ar": "البصري",
            "death_year": "148",
            "birth_year": "69",
            "reliability_grade": "Saduq",
            "tabaqat": "5",
            "location": "Basra"
          },
          {
            "name": "Anas ibn Malik",
            "full_name": "Anas ibn Malik ibn al-Nadr al-Ansari",
            "grade": "Thiqah Thabt",
            "generation": "Companion",
            "transmissionTerm": "عَنْ",
            "transmissionTermMeaning": "From",
            "reliabilityIssues": [],
            "narrator_id": 720,
            "alternative_names": "Anas al-Ansari",
            "original_id": 720,
            "kunya": "Abu Hamza",
            "nisba": "al-Ansari",
            "nisba_ar": "الأنصاري",
            "death_year": "93",
            "birth_year": "10",
            "reliability_grade": "Thiqah Thabt",
            "tabaqat": "Companion",
            "location": "Al-Madinah"
          },
          {
            "name": "Prophet Muhammad ﷺ",
            "full_name": "Muhammad ibn Abdullah ibn Abd al-Muttalib ibn Hashim",
            "grade": "Awthaq al-Nas",
            "generation": "Prophet",
            "transmissionTerm": "",
            "transmissionTermMeaning": "",
            "reliabilityIssues": [],
            "narrator_id": 0,
            "alternative_names": "Ahmad, al-Mustafa",
            "original_id": 0,
            "kunya": "Abu al-Qasim",
            "nisba": "al-Hashimi",
            "nisba_ar": "الهاشمي",
            "death_year": "11",
            "birth_year": "53 BH",
            "reliability_grade": "Awthaq al-Nas",
            "tabaqat": "Prophet",
            "location": "Makkah/Al-Madinah"
          }
        ],
        "chainIssues": [
          "Humaid narrates from Anas with 'an (عَنْ)",
          "This chain is stronger than the first one due to Yazid ibn Harun being Thabt Hafiz"
        ]
      },
      {
        "type": "marfu'",
        "narrators": [
          {
            "name": "Muhammad ibn al-Muthanna",
            "full_name": "Muhammad ibn al-Muthanna ibn Uthman al-Anzi al-Basri",
            "grade": "Thabt Hafiz",
            "generation": "Eighth Generation",
            "transmissionTerm": "حَدَّثَنَا",
            "transmissionTermMeaning": "He narrated to us (direct hearing)",
            "reliabilityIssues": [],
            "narrator_id": 6861,
            "alternative_names": "Muhammad al-Anzi, Abu Musa",
            "original_id": 6096,
            "kunya": "Abu Musa",
            "nisba": "al-Anzi",
            "nisba_ar": "العنزي",
            "death_year": "252",
            "birth_year": "167",
            "reliability_grade": "Thabt Hafiz",
            "tabaqat": "8",
            "location": "Basra"
          },
          {
            "name": "Khalid ibn al-Harith",
            "full_name": "Khalid ibn al-Harith ibn Yazid al-Azdi al-Qurashi",
            "grade": "Thabt Hafiz",
            "generation": "Seventh Generation",
            "transmissionTerm": "نَا",
            "transmissionTermMeaning": "He narrated to us (direct hearing)",
            "reliabilityIssues": [],
            "narrator_id": 2625,
            "alternative_names": "Khalid al-Azdi",
            "original_id": 1741,
            "kunya": "Abu al-Hasan",
            "nisba": "al-Azdi",
            "nisba_ar": "الأزدي",
            "death_year": "213",
            "birth_year": "132",
            "reliability_grade": "Thabt Hafiz",
            "tabaqat": "7",
            "location": "Basra"
          },
          {
            "name": "Humaid",
            "full_name": "Humaid ibn Abi Humaid al-Tawil al-Basri",
            "grade": "Saduq",
            "generation": "Fifth Generation",
            "transmissionTerm": "نَا",
            "transmissionTermMeaning": "He narrated to us (direct hearing)",
            "reliabilityIssues": [],
            "narrator_id": 2531,
            "alternative_names": "Humaid al-Basri",
            "original_id": 1645,
            "kunya": "Abu Muhammad",
            "nisba": "al-Basri",
            "nisba_ar": "البصري",
            "death_year": "148",
            "birth_year": "69",
            "reliability_grade": "Saduq",
            "tabaqat": "5",
            "location": "Basra"
          },
          {
            "name": "Anas ibn Malik",
            "full_name": "Anas ibn Malik ibn al-Nadr al-Ansari",
            "grade": "Thiqah Thabt",
            "generation": "Companion",
            "transmissionTerm": "عَنْ",
            "transmissionTermMeaning": "From",
            "reliabilityIssues": [],
            "narrator_id": 720,
            "alternative_names": "Anas al-Ansari",
            "original_id": 720,
            "kunya": "Abu Hamza",
            "nisba": "al-Ansari",
            "nisba_ar": "الأنصاري",
            "death_year": "93",
            "birth_year": "10",
            "reliability_grade": "Thiqah Thabt",
            "tabaqat": "Companion",
            "location": "Al-Madinah"
          },
          {
            "name": "Prophet Muhammad ﷺ",
            "full_name": "Muhammad ibn Abdullah ibn Abd al-Muttalib ibn Hashim",
            "grade": "Awthaq al-Nas",
            "generation": "Prophet",
            "transmissionTerm": "",
            "transmissionTermMeaning": "",
            "reliabilityIssues": [],
            "narrator_id": 0,
            "alternative_names": "Ahmad, al-Mustafa",
            "original_id": 0,
            "kunya": "Abu al-Qasim",
            "nisba": "al-Hashimi",
            "nisba_ar": "الهاشمي",
            "death_year": "11",
            "birth_year": "53 BH",
            "reliability_grade": "Awthaq al-Nas",
            "tabaqat": "Prophet",
            "location": "Makkah/Al-Madinah"
          }
        ],
        "chainIssues": [
          "Humaid narrates from Anas with 'an (عَنْ)",
          "This chain is strong with two Thabt Hafiz narrators at the beginning"
        ]
      }
    ],
    "potential_issues": [
      {
        "issue": "Khalid ibn Usamah (in first chain) is Saduq Lahu Awham",
        "impact": "The first chain is weakened by this narrator's confusion in transmissions"
      },
      {
        "issue": "Humaid narrates with عَنْ ('an) in all three chains",
        "impact": "While Humaid is Saduq and relatively reliable, the 'an term introduces slight ambiguity"
      },
      {
        "issue": "Convergence of chains through Humaid and Anas",
        "impact": "All three chains converge at Humaid's narration from Anas, but they come through different earlier narrators"
      }
    ],
    "Classical Grade": [
      "Hasan"
    ],
    "IISGrade": "Acceptable",
    "Topics": [
      "The Prophet's ﷺ ranking of Ansar houses",
      "Mention of Banu Harithah as one of the best Ansar houses",
      "Emphasis on the merit of all Ansar houses"
    ]
  },
  {
    "hadith_id": 270998,
    "book_id": 277,
    "book_name_ar": "كتاب رقم 277",
    "book_name_en": "Book 277 (Unknown Collection)",
    "author_name_ar": "مؤلف غير معروف",
    "author_name_en": "Unknown Author",
    "hadith_number": "2201",
    "english_translation": "Narrated by Sulayman ibn Bilal: The Prophet ﷺ said: The best houses of the Ansar are: Banu al-Najjar, then Banu Abd al-Ashhal, then Banu al-Harith ibn al-Khazraj, then Banu Sa'idah.",
    "chains": [
      {
        "type": "marfu'",
        "narrators": [
          {
            "name": "Muhammad ibn Ismail",
            "full_name": "Muhammad ibn Ismail ibn Ibrahim ibn al-Mughirah al-Bukhari",
            "grade": "Thabt Hafiz",
            "generation": "Ninth Generation",
            "transmissionTerm": "حَدَّثَنَا",
            "transmissionTermMeaning": "He narrated to us (direct hearing)",
            "reliabilityIssues": [],
            "narrator_id": 6817,
            "alternative_names": "Al-Bukhari, Imam al-Bukhari",
            "original_id": 6053,
            "kunya": "Abu Abdullah",
            "nisba": "al-Bukhari",
            "nisba_ar": "البخاري",
            "death_year": "256",
            "birth_year": "194",
            "reliability_grade": "Thabt Hafiz",
            "tabaqat": "9",
            "location": "Bukhara"
          },
          {
            "name": "Ibn Abi Uways",
            "full_name": "Abdullah ibn Muhammad ibn Abi Uways al-Medini al-Asbahi",
            "grade": "Saduq",
            "generation": "Seventh Generation",
            "transmissionTerm": "نَا",
            "transmissionTermMeaning": "He narrated to us (direct hearing)",
            "reliabilityIssues": [],
            "narrator_id": 1040,
            "alternative_names": "Abd Allah ibn Muhammad al-Medini",
            "original_id": 116,
            "kunya": "Abu Muhammad",
            "nisba": "al-Medini",
            "nisba_ar": "المديني",
            "death_year": "213",
            "birth_year": "135",
            "reliability_grade": "Saduq",
            "tabaqat": "7",
            "location": "Al-Madinah"
          },
          {
            "name": "His brother (Malik ibn Muhammad)",
            "full_name": "Malik ibn Muhammad ibn Abi Uways al-Asbahi",
            "grade": "Saduq",
            "generation": "Sixth Generation",
            "transmissionTerm": "نَا",
            "transmissionTermMeaning": "He narrated to us (direct hearing)",
            "reliabilityIssues": [],
            "narrator_id": 4244,
            "alternative_names": "Malik al-Asbahi",
            "original_id": 4124,
            "kunya": "Abu Muhammad",
            "nisba": "al-Asbahi",
            "nisba_ar": "الأصبحي",
            "death_year": "213",
            "birth_year": "125",
            "reliability_grade": "Saduq",
            "tabaqat": "6",
            "location": "Al-Madinah"
          },
          {
            "name": "Sulayman ibn Bilal",
            "full_name": "Sulayman ibn Bilal al-Qurashi al-Medini",
            "grade": "Saduq",
            "generation": "Fifth Generation",
            "transmissionTerm": "عَنْ",
            "transmissionTermMeaning": "From (could be direct or indirect)",
            "reliabilityIssues": [],
            "narrator_id": 3580,
            "alternative_names": "Sulayman ibn Bilal",
            "original_id": 2732,
            "kunya": "Abu Isa",
            "nisba": "al-Medini",
            "nisba_ar": "المديني",
            "death_year": "161",
            "birth_year": "80",
            "reliability_grade": "Saduq",
            "tabaqat": "5",
            "location": "Al-Madinah"
          },
          {
            "name": "Prophet Muhammad ﷺ",
            "full_name": "Muhammad ibn Abdullah ibn Abd al-Muttalib ibn Hashim",
            "grade": "Awthaq al-Nas",
            "generation": "Prophet",
            "transmissionTerm": "",
            "transmissionTermMeaning": "",
            "reliabilityIssues": [],
            "narrator_id": 0,
            "alternative_names": "Ahmad, al-Mustafa",
            "original_id": 0,
            "kunya": "Abu al-Qasim",
            "nisba": "al-Hashimi",
            "nisba_ar": "الهاشمي",
            "death_year": "11",
            "birth_year": "53 BH",
            "reliability_grade": "Awthaq al-Nas",
            "tabaqat": "Prophet",
            "location": "Makkah/Al-Madinah"
          }
        ],
        "chainIssues": [
          "Multiple Saduq-graded narrators in the chain",
          "Sulayman ibn Bilal uses عَنْ ('an)"
        ]
      }
    ],
    "potential_issues": [
      {
        "issue": "Three Saduq narrators in the chain (Ibn Abi Uways, Malik, Sulayman)",
        "impact": "Reduces reliability from Sound/Perfect to Acceptable or Weak"
      },
      {
        "issue": "Sulayman ibn Bilal narrates with عَنْ ('an)",
        "impact": "Introduces slight ambiguity in the connection, though this is acceptable with Saduq narrators who are not mudallis"
      }
    ],
    "Classical Grade": [
      "Hasan"
    ],
    "IISGrade": "Acceptable",
    "Topics": [
      "The Prophet's ﷺ praise of Ansar houses",
      "Ranking of four main Ansar houses"
    ]
  },
  {
    "hadith_id": 270999,
    "book_id": 277,
    "book_name_ar": "كتاب رقم 277",
    "book_name_en": "Book 277 (Unknown Collection)",
    "author_name_ar": "مؤلف غير معروف",
    "author_name_en": "Unknown Author",
    "hadith_number": "2202",
    "english_translation": "Banu al-Najjar are the maternal uncles of the Prophet ﷺ.",
    "chains": [],
    "potential_issues": [
      {
        "issue": "This is a chapter heading, not a hadith with a chain of transmission",
        "impact": "No chain to evaluate"
      }
    ],
    "Classical Grade": [
      "Daif"
    ],
    "IISGrade": "Disconnections But All Narrators Are Ok",
    "Topics": [
      "Genealogical relationship of Banu al-Najjar to the Prophet ﷺ"
    ]
  },
  {
    "hadith_id": 271000,
    "book_id": 277,
    "book_name_ar": "كتاب رقم 277",
    "book_name_en": "Book 277 (Unknown Collection)",
    "author_name_ar": "مؤلف غير معروف",
    "author_name_en": "Unknown Author",
    "hadith_number": "2203",
    "english_translation": "Narrated by Anas ibn Malik: The Prophet ﷺ said: The best houses of the Ansar are: Banu al-Najjar, then Banu al-Ashhal, then Banu al-Harith ibn al-Khazraj, then Banu Sa'idah, and in all houses of the Ansar there is good.",
    "chains": [
      {
        "type": "marfu'",
        "narrators": [
          {
            "name": "Wahban ibn Baqi'ah",
            "full_name": "Wahban ibn Baqi'ah al-Wasiti",
            "grade": "Saduq",
            "generation": "Eighth Generation",
            "transmissionTerm": "حَدَّثَنَا",
            "transmissionTermMeaning": "He narrated to us (direct hearing)",
            "reliabilityIssues": [],
            "narrator_id": 8166,
            "alternative_names": "Wahban al-Wasiti",
            "original_id": 7423,
            "kunya": "Abu Uthman",
            "nisba": "al-Wasiti",
            "nisba_ar": "الواسطي",
            "death_year": "235",
            "birth_year": "160",
            "reliability_grade": "Saduq",
            "tabaqat": "8",
            "location": "Wasit"
          },
          {
            "name": "Khalid",
            "full_name": "Khalid ibn Usamah al-Hamdani",
            "grade": "Saduq Lahu Awham",
            "generation": "Seventh Generation",
            "transmissionTerm": "نَا",
            "transmissionTermMeaning": "He narrated to us (direct hearing)",
            "reliabilityIssues": [
              "has confusion in his narrations"
            ],
            "narrator_id": 2663,
            "alternative_names": "Khalid al-Hamdani",
            "original_id": 1779,
            "kunya": "Abu Usamah",
            "nisba": "al-Hamdani",
            "nisba_ar": "الهمداني",
            "death_year": "208",
            "birth_year": "129",
            "reliability_grade": "Saduq Lahu Awham",
            "tabaqat": "7",
            "location": "Kufa"
          },
          {
            "name": "Humaid",
            "full_name": "Humaid ibn Abi Humaid al-Tawil al-Basri",
            "grade": "Saduq",
            "generation": "Fifth Generation",
            "transmissionTerm": "عَنْ",
            "transmissionTermMeaning": "From (could be direct or indirect)",
            "reliabilityIssues": [],
            "narrator_id": 2531,
            "alternative_names": "Humaid al-Basri",
            "original_id": 1645,
            "kunya": "Abu Muhammad",
            "nisba": "al-Basri",
            "nisba_ar": "البصري",
            "death_year": "148",
            "birth_year": "69",
            "reliability_grade": "Saduq",
            "tabaqat": "5",
            "location": "Basra"
          },
          {
            "name": "Anas ibn Malik",
            "full_name": "Anas ibn Malik ibn al-Nadr al-Ansari",
            "grade": "Thiqah Thabt",
            "generation": "Companion",
            "transmissionTerm": "عَنْ",
            "transmissionTermMeaning": "From",
            "reliabilityIssues": [],
            "narrator_id": 720,
            "alternative_names": "Anas al-Ansari",
            "original_id": 720,
            "kunya": "Abu Hamza",
            "nisba": "al-Ansari",
            "nisba_ar": "الأنصاري",
            "death_year": "93",
            "birth_year": "10",
            "reliability_grade": "Thiqah Thabt",
            "tabaqat": "Companion",
            "location": "Al-Madinah"
          },
          {
            "name": "Prophet Muhammad ﷺ",
            "full_name": "Muhammad ibn Abdullah ibn Abd al-Muttalib ibn Hashim",
            "grade": "Awthaq al-Nas",
            "generation": "Prophet",
            "transmissionTerm": "",
            "transmissionTermMeaning": "",
            "reliabilityIssues": [],
            "narrator_id": 0,
            "alternative_names": "Ahmad, al-Mustafa",
            "original_id": 0,
            "kunya": "Abu al-Qasim",
            "nisba": "al-Hashimi",
            "nisba_ar": "الهاشمي",
            "death_year": "11",
            "birth_year": "53 BH",
            "reliability_grade": "Awthaq al-Nas",
            "tabaqat": "Prophet",
            "location": "Makkah/Al-Madinah"
          }
        ],
        "chainIssues": [
          "Khalid ibn Usamah has Saduq Lahu Awham rating",
          "Humaid narrates with عَنْ ('an)"
        ]
      }
    ],
    "potential_issues": [
      {
        "issue": "Khalid ibn Usamah is rated Saduq Lahu Awham (has confusion in narrations)",
        "impact": "Weakens the chain reliability"
      },
      {
        "issue": "Multiple Saduq narrators with 'an transmission",
        "impact": "Reduces reliability to Acceptable level"
      }
    ],
    "Classical Grade": [
      "Hasan"
    ],
    "IISGrade": "Acceptable",
    "Topics": [
      "The Prophet's ﷺ ranking of Ansar houses",
      "Merit of all Ansar houses"
    ]
  },
  {
    "hadith_id": 271001,
    "book_id": 277,
    "book_name_ar": "كتاب رقم 277",
    "book_name_en": "Book 277 (Unknown Collection)",
    "author_name_ar": "مؤلف غير معروف",
    "author_name_en": "Unknown Author",
    "hadith_number": "2204",
    "english_translation": "Narrated by Abu Khalid: I heard Humaid from Anas ibn Malik: The Prophet ﷺ said: The best houses of the Ansar are: Banu al-Najjar, then Banu al-Ashhal, then Banu al-Harith ibn al-Khazraj, then Banu Sa'idah.",
    "chains": [
      {
        "type": "marfu'",
        "narrators": [
          {
            "name": "Abu Saeed al-Ashaj",
            "full_name": "Talha ibn Uthman ibn Sharik al-Qurashi",
            "grade": "Thabt Hafiz",
            "generation": "Eighth Generation",
            "transmissionTerm": "حَدَّثَنَا",
            "transmissionTermMeaning": "He narrated to us (direct hearing)",
            "reliabilityIssues": [],
            "narrator_id": 4836,
            "alternative_names": "Abu Saeed al-Ashaj al-Basri",
            "original_id": 4003,
            "kunya": "Abu Saeed",
            "nisba": "al-Qurashi",
            "nisba_ar": "القرشي",
            "death_year": "212",
            "birth_year": "130",
            "reliability_grade": "Thabt Hafiz",
            "tabaqat": "8",
            "location": "Basra"
          },
          {
            "name": "Abu Khalid al-Qurashi",
            "full_name": "Abd al-Rahman ibn Khalid al-Qurashi al-Medini",
            "grade": "Saduq",
            "generation": "Fifth Generation",
            "transmissionTerm": "سَمِعْتُ",
            "transmissionTermMeaning": "I heard (direct hearing)",
            "reliabilityIssues": [],
            "narrator_id": 3580,
            "alternative_names": "Abu Khalid",
            "original_id": 2732,
            "kunya": "Abu Khalid",
            "nisba": "al-Medini",
            "nisba_ar": "المديني",
            "death_year": "161",
            "birth_year": "80",
            "reliability_grade": "Saduq",
            "tabaqat": "5",
            "location": "Al-Madinah"
          },
          {
            "name": "Humaid",
            "full_name": "Humaid ibn Abi Humaid al-Tawil al-Basri",
            "grade": "Saduq",
            "generation": "Fifth Generation",
            "transmissionTerm": "قَالَ",
            "transmissionTermMeaning": "He said",
            "reliabilityIssues": [],
            "narrator_id": 2531,
            "alternative_names": "Humaid al-Basri",
            "original_id": 1645,
            "kunya": "Abu Muhammad",
            "nisba": "al-Basri",
            "nisba_ar": "البصري",
            "death_year": "148",
            "birth_year": "69",
            "reliability_grade": "Saduq",
            "tabaqat": "5",
            "location": "Basra"
          },
          {
            "name": "Anas ibn Malik",
            "full_name": "Anas ibn Malik ibn al-Nadr al-Ansari",
            "grade": "Thiqah Thabt",
            "generation": "Companion",
            "transmissionTerm": "عَنْ",
            "transmissionTermMeaning": "From",
            "reliabilityIssues": [],
            "narrator_id": 720,
            "alternative_names": "Anas al-Ansari",
            "original_id": 720,
            "kunya": "Abu Hamza",
            "nisba": "al-Ansari",
            "nisba_ar": "الأنصاري",
            "death_year": "93",
            "birth_year": "10",
            "reliability_grade": "Thiqah Thabt",
            "tabaqat": "Companion",
            "location": "Al-Madinah"
          },
          {
            "name": "Prophet Muhammad ﷺ",
            "full_name": "Muhammad ibn Abdullah ibn Abd al-Muttalib ibn Hashim",
            "grade": "Awthaq al-Nas",
            "generation": "Prophet",
            "transmissionTerm": "",
            "transmissionTermMeaning": "",
            "reliabilityIssues": [],
            "narrator_id": 0,
            "alternative_names": "Ahmad, al-Mustafa",
            "original_id": 0,
            "kunya": "Abu al-Qasim",
            "nisba": "al-Hashimi",
            "nisba_ar": "الهاشمي",
            "death_year": "11",
            "birth_year": "53 BH",
            "reliability_grade": "Awthaq al-Nas",
            "tabaqat": "Prophet",
            "location": "Makkah/Al-Madinah"
          }
        ],
        "chainIssues": []
      }
    ],
    "potential_issues": [
      {
        "issue": "Abu Khalid and Humaid are both Saduq narrators",
        "impact": "Slightly reduces reliability but still acceptable"
      }
    ],
    "Classical Grade": [
      "Hasan"
    ],
    "IISGrade": "Acceptable",
    "Topics": [
      "The Prophet's ﷺ ranking of Ansar houses",
      "Merit of four main Ansar tribes"
    ]
  },
  {
    "hadith_id": 271002,
    "book_id": 277,
    "book_name_ar": "كتاب رقم 277",
    "book_name_en": "Book 277 (Unknown Collection)",
    "author_name_ar": "مؤلف غير معروف",
    "author_name_en": "Unknown Author",
    "hadith_number": "2205",
    "english_translation": "Narrated by Yahya ibn Saeed: I heard the Prophet ﷺ say: The best houses of the Ansar are: Banu al-Najjar, then Banu al-Ashhal, then Banu al-Harith ibn al-Khazraj, then Banu Sa'idah.",
    "chains": [
      {
        "type": "marfu'",
        "narrators": [
          {
            "name": "Muhammad ibn al-Muthanna",
            "full_name": "Muhammad ibn al-Muthanna ibn Uthman al-Anzi al-Basri",
            "grade": "Thabt Hafiz",
            "generation": "Eighth Generation",
            "transmissionTerm": "حَدَّثَنَا",
            "transmissionTermMeaning": "He narrated to us (direct hearing)",
            "reliabilityIssues": [],
            "narrator_id": 6861,
            "alternative_names": "Muhammad al-Anzi, Abu Musa",
            "original_id": 6096,
            "kunya": "Abu Musa",
            "nisba": "al-Anzi",
            "nisba_ar": "العنزي",
            "death_year": "252",
            "birth_year": "167",
            "reliability_grade": "Thabt Hafiz",
            "tabaqat": "8",
            "location": "Basra"
          },
          {
            "name": "Abd al-Wahhab ibn Abd al-Majid",
            "full_name": "Abd al-Wahhab ibn Abd al-Majid ibn Abd al-Aziz al-Thaqafi",
            "grade": "Thabt Hafiz",
            "generation": "Seventh Generation",
            "transmissionTerm": "نَا",
            "transmissionTermMeaning": "He narrated to us (direct hearing)",
            "reliabilityIssues": [],
            "narrator_id": 5280,
            "alternative_names": "Abd al-Wahhab al-Thaqafi",
            "original_id": 4461,
            "kunya": "Abu Muhammad",
            "nisba": "al-Thaqafi",
            "nisba_ar": "الثقفي",
            "death_year": "194",
            "birth_year": "113",
            "reliability_grade": "Thabt Hafiz",
            "tabaqat": "7",
            "location": "Basra"
          },
          {
            "name": "Yahya ibn Saeed al-Qattan",
            "full_name": "Yahya ibn Saeed ibn Farruakh al-Tamimi al-Basri",
            "grade": "Thabt Hafiz",
            "generation": "Fifth Generation",
            "transmissionTerm": "سَمِعْتُ",
            "transmissionTermMeaning": "I heard (direct hearing)",
            "reliabilityIssues": [],
            "narrator_id": 8272,
            "alternative_names": "Yahya al-Qattan",
            "original_id": 7533,
            "kunya": "Abu Zakariya",
            "nisba": "al-Basri",
            "nisba_ar": "البصري",
            "death_year": "198",
            "birth_year": "120",
            "reliability_grade": "Thabt Hafiz",
            "tabaqat": "5",
            "location": "Basra"
          },
          {
            "name": "Prophet Muhammad ﷺ",
            "full_name": "Muhammad ibn Abdullah ibn Abd al-Muttalib ibn Hashim",
            "grade": "Awthaq al-Nas",
            "generation": "Prophet",
            "transmissionTerm": "",
            "transmissionTermMeaning": "",
            "reliabilityIssues": [],
            "narrator_id": 0,
            "alternative_names": "Ahmad, al-Mustafa",
            "original_id": 0,
            "kunya": "Abu al-Qasim",
            "nisba": "al-Hashimi",
            "nisba_ar": "الهاشمي",
            "death_year": "11",
            "birth_year": "53 BH",
            "reliability_grade": "Awthaq al-Nas",
            "tabaqat": "Prophet",
            "location": "Makkah/Al-Madinah"
          }
        ],
        "chainIssues": []
      }
    ],
    "potential_issues": [],
    "Classical Grade": [
      "Sahih"
    ],
    "IISGrade": "Sound",
    "Topics": [
      "The Prophet's ﷺ ranking of the best Ansar houses",
      "Merit of four main Ansar tribes"
    ]
  },
  {
    "hadith_id": 271003,
    "book_id": 277,
    "book_name_ar": "كتاب رقم 277",
    "book_name_en": "Book Number 277",
    "author_name_ar": "مؤلف غير معروف",
    "author_name_en": "Unknown Author",
    "hadith_number": "2206",
    "english_translation": "Narrated by Anas: The Messenger of Allah ﷺ loved that the Muhajirun and Ansar would be close to him so they could learn from him.",
    "chains": [
      {
        "type": "marfu'",
        "narrators": [
          {
            "name": "أبو بكر بن أبي شيبة",
            "full_name": "عبد الله بن محمد بن أبي شيبة إبراهيم بن عثمان العبسي",
            "grade": "Thabt Hafiz",
            "generation": "Ninth Generation",
            "transmissionTerm": "حَدَّثَنَا",
            "transmissionTermMeaning": "He narrated to us (direct hearing)",
            "reliabilityIssues": [],
            "narrator_id": 5049,
            "alternative_names": "Abdullah ibn Muhammad, Ibn Abi Shaybah",
            "original_id": 5049,
            "kunya": "أبو بكر",
            "nisba": "العبسي الكوفي",
            "nisba_ar": "العبسي الكوفي",
            "death_year": "235",
            "birth_year": "159",
            "reliability_grade": "Thabt Hafiz",
            "tabaqat": "Ninth",
            "location": "Kufa"
          },
          {
            "name": "عبد الوهاب الثقفي",
            "full_name": "عبد الوهاب بن عبد المجيد بن الصلت الثقفي",
            "grade": "Thiqah Thabt",
            "generation": "Eighth Generation",
            "transmissionTerm": "نا",
            "transmissionTermMeaning": "He narrated to us (direct hearing, abbreviated)",
            "reliabilityIssues": [],
            "narrator_id": 5280,
            "alternative_names": "Abd al-Wahhab ibn Abd al-Majid",
            "original_id": 5280,
            "kunya": "أبو محمد",
            "nisba": "الثقفي البصري",
            "nisba_ar": "الثقفي البصري",
            "death_year": "194",
            "birth_year": "110",
            "reliability_grade": "Thiqah Thabt",
            "tabaqat": "Eighth",
            "location": "Basra"
          },
          {
            "name": "حميد",
            "full_name": "حميد بن أبي حميد الطويل",
            "grade": "Thiqah",
            "generation": "Fifth Generation",
            "transmissionTerm": "عَنْ",
            "transmissionTermMeaning": "From (could be direct or indirect)",
            "reliabilityIssues": [],
            "narrator_id": 2531,
            "alternative_names": "Humayd al-Tawil",
            "original_id": 2531,
            "kunya": "أبو عبيدة",
            "nisba": "الطويل البصري",
            "nisba_ar": "الطويل البصري",
            "death_year": "143",
            "birth_year": "",
            "reliability_grade": "Thiqah",
            "tabaqat": "Fifth",
            "location": "Basra"
          },
          {
            "name": "أنس",
            "full_name": "أنس بن مالك بن النضر الأنصاري",
            "grade": "Thiqah Thabt",
            "generation": "Companion",
            "transmissionTerm": "عَنْ",
            "transmissionTermMeaning": "From (could be direct or indirect)",
            "reliabilityIssues": [],
            "narrator_id": 720,
            "alternative_names": "Anas ibn Malik",
            "original_id": 720,
            "kunya": "أبو حمزة",
            "nisba": "الأنصاري",
            "nisba_ar": "الأنصاري",
            "death_year": "93",
            "birth_year": "10 BH",
            "reliability_grade": "Thiqah Thabt",
            "tabaqat": "Companion",
            "location": "Basra/Madinah"
          },
          {
            "name": "Prophet Muhammad ﷺ",
            "full_name": "Muhammad ibn Abdullah ibn Abd al-Muttalib ibn Hashim",
            "grade": "Awthaq al-Nas",
            "generation": "Prophet",
            "transmissionTerm": "",
            "transmissionTermMeaning": "",
            "reliabilityIssues": [],
            "narrator_id": 0,
            "alternative_names": "Ahmad, al-Mustafa, Rasulullah",
            "original_id": 0,
            "kunya": "Abu al-Qasim",
            "nisba": "al-Hashimi al-Qurashi",
            "nisba_ar": "الهاشمي القرشي",
            "death_year": "11",
            "birth_year": "53 BH",
            "reliability_grade": "Awthaq al-Nas",
            "tabaqat": "Prophet",
            "location": "Makkah/Madinah"
          }
        ],
        "chainIssues": [
          "Humayd narrates from Anas using 'an (indirect form), though connection is established"
        ]
      }
    ],
    "potential_issues": [
      {
        "issue": "Humayd narrates from Anas using 'an (indirect form), though connection is established",
        "impact": "May affect chain grading"
      }
    ],
    "Classical Grade": [
      "Sahih"
    ],
    "IISGrade": "Sound",
    "Topics": [
      "Prophet's love for Muhajirun and Ansar",
      "Companions learning from the Prophet",
      "Virtue of proximity to the Prophet"
    ]
  },
  {
    "hadith_id": 271004,
    "book_id": 277,
    "book_name_ar": "كتاب رقم 277",
    "book_name_en": "Book Number 277",
    "author_name_ar": "مؤلف غير معروف",
    "author_name_en": "Unknown Author",
    "hadith_number": "2207",
    "english_translation": "Narrated by Anas: The Messenger of Allah ﷺ loved that the Muhajirun and Ansar would be close to him.",
    "chains": [
      {
        "type": "marfu'",
        "narrators": [
          {
            "name": "الشافعي",
            "full_name": "محمد بن إدريس بن العباس بن عثمان بن شافع",
            "grade": "Thabt Hafiz",
            "generation": "Ninth Generation",
            "transmissionTerm": "حَدَّثَنَا",
            "transmissionTermMeaning": "He narrated to us (direct hearing)",
            "reliabilityIssues": [],
            "narrator_id": 872,
            "alternative_names": "Imam al-Shafi'i, Muhammad ibn Idris",
            "original_id": 872,
            "kunya": "أبو عبد الله",
            "nisba": "القرشي الشافعي",
            "nisba_ar": "القرشي الشافعي",
            "death_year": "204",
            "birth_year": "150",
            "reliability_grade": "Thabt Hafiz",
            "tabaqat": "Ninth",
            "location": "Makkah/Egypt"
          },
          {
            "name": "حميد",
            "full_name": "حميد بن أبي حميد الطويل",
            "grade": "Thiqah",
            "generation": "Fifth Generation",
            "transmissionTerm": "عَنْ",
            "transmissionTermMeaning": "From (could be direct or indirect)",
            "reliabilityIssues": [],
            "narrator_id": 2531,
            "alternative_names": "Humayd al-Tawil",
            "original_id": 2531,
            "kunya": "أبو عبيدة",
            "nisba": "الطويل البصري",
            "nisba_ar": "الطويل البصري",
            "death_year": "143",
            "birth_year": "",
            "reliability_grade": "Thiqah",
            "tabaqat": "Fifth",
            "location": "Basra"
          },
          {
            "name": "أنس",
            "full_name": "أنس بن مالك بن النضر الأنصاري",
            "grade": "Thiqah Thabt",
            "generation": "Companion",
            "transmissionTerm": "عَنْ",
            "transmissionTermMeaning": "From (could be direct or indirect)",
            "reliabilityIssues": [],
            "narrator_id": 720,
            "alternative_names": "Anas ibn Malik",
            "original_id": 720,
            "kunya": "أبو حمزة",
            "nisba": "الأنصاري",
            "nisba_ar": "الأنصاري",
            "death_year": "93",
            "birth_year": "10 BH",
            "reliability_grade": "Thiqah Thabt",
            "tabaqat": "Companion",
            "location": "Basra/Madinah"
          },
          {
            "name": "Prophet Muhammad ﷺ",
            "full_name": "Muhammad ibn Abdullah ibn Abd al-Muttalib ibn Hashim",
            "grade": "Awthaq al-Nas",
            "generation": "Prophet",
            "transmissionTerm": "",
            "transmissionTermMeaning": "",
            "reliabilityIssues": [],
            "narrator_id": 0,
            "alternative_names": "Ahmad, al-Mustafa, Rasulullah",
            "original_id": 0,
            "kunya": "Abu al-Qasim",
            "nisba": "al-Hashimi al-Qurashi",
            "nisba_ar": "الهاشمي القرشي",
            "death_year": "11",
            "birth_year": "53 BH",
            "reliability_grade": "Awthaq al-Nas",
            "tabaqat": "Prophet",
            "location": "Makkah/Madinah"
          }
        ],
        "chainIssues": []
      }
    ],
    "potential_issues": [],
    "Classical Grade": [
      "Sahih"
    ],
    "IISGrade": "Sound",
    "Topics": [
      "Prophet's love for Muhajirun and Ansar",
      "Companions learning from the Prophet"
    ]
  },
  {
    "hadith_id": 271005,
    "book_id": 277,
    "book_name_ar": "كتاب رقم 277",
    "book_name_en": "Book Number 277",
    "author_name_ar": "مؤلف غير معروف",
    "author_name_en": "Unknown Author",
    "hadith_number": "2208",
    "english_translation": "Narrated by Anas: When the Messenger of Allah ﷺ arrived in Madinah, the Prophet ﷺ established brotherhood between Abd al-Rahman and Sa'd ibn al-Rabi'. Sa'd said to him: 'The Ansar know that I am the wealthiest among them, so I will divide my wealth with you in half, and I have two wives, so see which one you prefer and I will divorce her, and when her waiting period ends, you can marry her.' Abd al-Rahman said: 'May Allah bless you in your family and wealth. Show me the market.'",
    "chains": [
      {
        "type": "marfu'",
        "narrators": [
          {
            "name": "الشافعي",
            "full_name": "محمد بن إدريس بن العباس بن عثمان بن شافع",
            "grade": "Thabt Hafiz",
            "generation": "Ninth Generation",
            "transmissionTerm": "حَدَّثَنَا",
            "transmissionTermMeaning": "He narrated to us (direct hearing)",
            "reliabilityIssues": [],
            "narrator_id": 872,
            "alternative_names": "Imam al-Shafi'i",
            "original_id": 872,
            "kunya": "أبو عبد الله",
            "nisba": "القرشي الشافعي",
            "nisba_ar": "القرشي الشافعي",
            "death_year": "204",
            "birth_year": "150",
            "reliability_grade": "Thabt Hafiz",
            "tabaqat": "Ninth",
            "location": "Makkah/Egypt"
          },
          {
            "name": "حميد",
            "full_name": "حميد بن أبي حميد الطويل",
            "grade": "Thiqah",
            "generation": "Fifth Generation",
            "transmissionTerm": "عَنْ",
            "transmissionTermMeaning": "From (could be direct or indirect)",
            "reliabilityIssues": [],
            "narrator_id": 2531,
            "alternative_names": "Humayd al-Tawil",
            "original_id": 2531,
            "kunya": "أبو عبيدة",
            "nisba": "الطويل البصري",
            "nisba_ar": "الطويل البصري",
            "death_year": "143",
            "birth_year": "",
            "reliability_grade": "Thiqah",
            "tabaqat": "Fifth",
            "location": "Basra"
          },
          {
            "name": "أنس",
            "full_name": "أنس بن مالك بن النضر الأنصاري",
            "grade": "Thiqah Thabt",
            "generation": "Companion",
            "transmissionTerm": "عَنْ",
            "transmissionTermMeaning": "From (could be direct or indirect)",
            "reliabilityIssues": [],
            "narrator_id": 720,
            "alternative_names": "Anas ibn Malik",
            "original_id": 720,
            "kunya": "أبو حمزة",
            "nisba": "الأنصاري",
            "nisba_ar": "الأنصاري",
            "death_year": "93",
            "birth_year": "10 BH",
            "reliability_grade": "Thiqah Thabt",
            "tabaqat": "Companion",
            "location": "Basra/Madinah"
          },
          {
            "name": "Prophet Muhammad ﷺ",
            "full_name": "Muhammad ibn Abdullah ibn Abd al-Muttalib ibn Hashim",
            "grade": "Awthaq al-Nas",
            "generation": "Prophet",
            "transmissionTerm": "",
            "transmissionTermMeaning": "",
            "reliabilityIssues": [],
            "narrator_id": 0,
            "alternative_names": "Ahmad, al-Mustafa, Rasulullah",
            "original_id": 0,
            "kunya": "Abu al-Qasim",
            "nisba": "al-Hashimi al-Qurashi",
            "nisba_ar": "الهاشمي القرشي",
            "death_year": "11",
            "birth_year": "53 BH",
            "reliability_grade": "Awthaq al-Nas",
            "tabaqat": "Prophet",
            "location": "Makkah/Madinah"
          }
        ],
        "chainIssues": []
      }
    ],
    "potential_issues": [],
    "Classical Grade": [
      "Sahih"
    ],
    "IISGrade": "Perfect",
    "Topics": [
      "Brotherhood between Muhajirun and Ansar",
      "Generosity of Sa'd ibn al-Rabi'",
      "Self-reliance of Abd al-Rahman ibn Awf",
      "Request to be shown the market",
      "Ansar offering wealth to Muhajirun"
    ]
  }
]